Metadata-Version: 2.1
Name: modelaverage
Version: 1.0.1
Summary: tf-keras, make the average of model weight in same models
Home-page: https://github.com/graykode/modelaverage
Author: Tae Hwan Jung(@graykode)
Author-email: nlkey2022@gmail.com
License: MIT
Keywords: pytorch model summary model.summary()
Platform: UNKNOWN
